[
    {
      "property_id": 16,
      "property_name": "My Property # 16",
      "total_floor": 3,
      "category_name": "Four Occupancy",
      "property_type_id": 1,
      "Property_Loc": "M G Road,Bangalore",
      "Property_image": "https://img.staticmb.com/mbimages/project/Photo_h310_w462/2021/04/26/Project-Photo-3-Sai-Florence-Chennai-5257515_600_800_310_462.jpg",
      "img_ct": 1,
      "video_ct": 0,
      "total_rooms": 36,
      "rooms_available": 36,
      "rooms_oocupied": 0
    },
    {
      "property_id": 14,
      "property_name": "Nest Homes",
      "total_floor": 3,
      "category_name": "Four Occupancy",
      "property_type_id": 1,
      "Property_Loc": "M G Road,Bangalore",
      "Property_image": "http://cdn.home-designing.com/wp-content/uploads/2022/05/green-living-room.jpg",
      "img_ct": 2,
      "video_ct": 0,
      "total_rooms": 36,
      "rooms_available": 36,
      "rooms_oocupied": 0
    },
    {
      "property_id": 19,
      "property_name": "My Property # 19",
      "total_floor": 3,
      "category_name": "Double Occupancy",
      "property_type_id": 1,
      "Property_Loc": "M G Road,Bangalore",
      "Property_image": "http://cdn.home-designing.com/wp-content/uploads/2022/05/Brazilian-summer-house.jpg",
      "img_ct": 1,
      "video_ct": 0,
      "total_rooms": 27,
      "rooms_available": 27,
      "rooms_oocupied": 0
    },
    {
      "property_id": 15,
      "property_name": "My Property # 15",
      "total_floor": 3,
      "category_name": "Double Occupancy",
      "property_type_id": 1,
      "Property_Loc": "M G Road,Bangalore",
      "Property_image": "http://cdn.home-designing.com/wp-content/uploads/2022/05/terazzo-pillar.jpg",
      "img_ct": 1,
      "video_ct": 0,
      "total_rooms": 27,
      "rooms_available": 27,
      "rooms_oocupied": 0
    },
    {
      "property_id": 5,
      "property_name": "My Property # 5",
      "total_floor": 3,
      "category_name": "Single Occupancy",
      "property_type_id": 1,
      "Property_Loc": "M G Road,Bangalore",
      "Property_image": "http://cdn.home-designing.com/wp-content/uploads/2022/05/home-design-Indonesia.jpg",
      "img_ct": 1,
      "video_ct": 0,
      "total_rooms": 9,
      "rooms_available": 9,
      "rooms_oocupied": 0
    },
    {
      "property_id": 13,
      "property_name": "New Property # 13",
      "total_floor": 3,
      "category_name": "Triple Occupancy",
      "property_type_id": 1,
      "Property_Loc": "M G Road,Bangalore",
      "Property_image": "http://cdn.home-designing.com/wp-content/uploads/2022/05/home-design-Indonesia.jpg",
      "img_ct": 1,
      "video_ct": 0,
      "total_rooms": 18,
      "rooms_available": 18,
      "rooms_oocupied": 0
    },
    {
      "property_id": 17,
      "property_name": "New Property # 17",
      "total_floor": 3,
      "category_name": "Single Occupancy",
      "property_type_id": 1,
      "Property_Loc": "M G Road,Bangalore",
      "Property_image": "http://cdn.home-designing.com/wp-content/uploads/2014/07/three-bedroom-floor-plans.jpeg",
      "img_ct": 1,
      "video_ct": 0,
      "total_rooms": 9,
      "rooms_available": 9,
      "rooms_oocupied": 0
    },
    {
      "property_id": 21,
      "property_name": "My Home # 21",
      "total_floor": 3,
      "category_name": "Double Occupancy",
      "property_type_id": 1,
      "Property_Loc": "M G Road,Bangalore",
      "Property_image": "http://cdn.home-designing.com/wp-content/uploads/2022/05/home-design-Indonesia.jpg",
      "img_ct": 1,
      "video_ct": 0,
      "total_rooms": 27,
      "rooms_available": 27,
      "rooms_oocupied": 0
    },
    {
      "property_id": 10,
      "property_name": "suriyas avenue",
      "total_floor": 3,
      "category_name": "Triple Occupancy",
      "property_type_id": 1,
      "Property_Loc": "M G Road,Bangalore",
      "Property_image": "http://cdn.home-designing.com/wp-content/uploads/2016/01/inspiring-bedroom-accent-wall.jpg",
      "img_ct": 1,
      "video_ct": 0,
      "total_rooms": 18,
      "rooms_available": 18,
      "rooms_oocupied": 0
    },
    {
      "property_id": 3,
      "property_name": "suriyas avenue",
      "total_floor": 3,
      "category_name": "Double Occupancy",
      "property_type_id": 1,
      "Property_Loc": "M G Road,Bangalore",
      "Property_image": "http://cdn.home-designing.com/wp-content/uploads/2022/05/home-design-Indonesia.jpg",
      "img_ct": 2,
      "video_ct": 0,
      "total_rooms": 27,
      "rooms_available": 27,
      "rooms_oocupied": 0
    },
    {
      "property_id": 14,
      "property_name": "Nest Homes",
      "total_floor": 3,
      "category_name": "Single Occupancy",
      "property_type_id": 1,
      "Property_Loc": "M G Road,Bangalore",
      "Property_image": "http://cdn.home-designing.com/wp-content/uploads/2022/05/green-living-room.jpg",
      "img_ct": 2,
      "video_ct": 0,
      "total_rooms": 9,
      "rooms_available": 9,
      "rooms_oocupied": 0
    },
    {
      "property_id": 7,
      "property_name": "New Property # 7",
      "total_floor": 3,
      "category_name": "Double Occupancy",
      "property_type_id": 1,
      "Property_Loc": "M G Road,Bangalore",
      "Property_image": "http://cdn.home-designing.com/wp-content/uploads/2022/05/terazzo-pillar.jpg",
      "img_ct": 1,
      "video_ct": 0,
      "total_rooms": 27,
      "rooms_available": 27,
      "rooms_oocupied": 0
    },
    {
      "property_id": 15,
      "property_name": "My Property # 15",
      "total_floor": 3,
      "category_name": "Triple Occupancy",
      "property_type_id": 1,
      "Property_Loc": "M G Road,Bangalore",
      "Property_image": "http://cdn.home-designing.com/wp-content/uploads/2022/05/terazzo-pillar.jpg",
      "img_ct": 1,
      "video_ct": 0,
      "total_rooms": 18,
      "rooms_available": 18,
      "rooms_oocupied": 0
    },
    {
      "property_id": 22,
      "property_name": "My Home # 22",
      "total_floor": 3,
      "category_name": "Triple Occupancy",
      "property_type_id": 1,
      "Property_Loc": "M G Road,Bangalore",
      "Property_image": "http://cdn.home-designing.com/wp-content/uploads/2022/05/modern-house-with-pool.jpg",
      "img_ct": 1,
      "video_ct": 0,
      "total_rooms": 18,
      "rooms_available": 18,
      "rooms_oocupied": 0
    },
    {
      "property_id": 8,
      "property_name": "My Home # 8",
      "total_floor": 3,
      "category_name": "Single Occupancy",
      "property_type_id": 1,
      "Property_Loc": "M G Road,Bangalore",
      "Property_image": "https://img.staticmb.com/mbimages/project/Photo_h310_w462/2021/04/26/Project-Photo-3-Sai-Florence-Chennai-5257515_600_800_310_462.jpg",
      "img_ct": 1,
      "video_ct": 0,
      "total_rooms": 9,
      "rooms_available": 9,
      "rooms_oocupied": 0
    },
    {
      "property_id": 21,
      "property_name": "My Home # 21",
      "total_floor": 3,
      "category_name": "Single Occupancy",
      "property_type_id": 1,
      "Property_Loc": "M G Road,Bangalore",
      "Property_image": "http://cdn.home-designing.com/wp-content/uploads/2022/05/home-design-Indonesia.jpg",
      "img_ct": 1,
      "video_ct": 0,
      "total_rooms": 9,
      "rooms_available": 9,
      "rooms_oocupied": 0
    },
    {
      "property_id": 23,
      "property_name": "New Property # 23",
      "total_floor": 3,
      "category_name": "Double Occupancy",
      "property_type_id": 1,
      "Property_Loc": "M G Road,Bangalore",
      "Property_image": "http://cdn.home-designing.com/wp-content/uploads/2022/05/terazzo-pillar.jpg",
      "img_ct": 1,
      "video_ct": 0,
      "total_rooms": 27,
      "rooms_available": 27,
      "rooms_oocupied": 0
    },
    {
      "property_id": 4,
      "property_name": "Ranka View Apartment",
      "total_floor": 3,
      "category_name": "Four Occupancy",
      "property_type_id": 1,
      "Property_Loc": "M G Road,Bangalore",
      "Property_image": "http://cdn.home-designing.com/wp-content/uploads/2022/05/modern-house-with-pool.jpg",
      "img_ct": 2,
      "video_ct": 0,
      "total_rooms": 36,
      "rooms_available": 36,
      "rooms_oocupied": 0
    },
    {
      "property_id": 20,
      "property_name": "New Property # 20",
      "total_floor": 3,
      "category_name": "Four Occupancy",
      "property_type_id": 1,
      "Property_Loc": "M G Road,Bangalore",
      "Property_image": "http://cdn.home-designing.com/wp-content/uploads/2022/05/green-living-room.jpg",
      "img_ct": 1,
      "video_ct": 0,
      "total_rooms": 36,
      "rooms_available": 36,
      "rooms_oocupied": 0
    },
    {
      "property_id": 16,
      "property_name": "My Property # 16",
      "total_floor": 3,
      "category_name": "Double Occupancy",
      "property_type_id": 1,
      "Property_Loc": "M G Road,Bangalore",
      "Property_image": "https://img.staticmb.com/mbimages/project/Photo_h310_w462/2021/04/26/Project-Photo-3-Sai-Florence-Chennai-5257515_600_800_310_462.jpg",
      "img_ct": 1,
      "video_ct": 0,
      "total_rooms": 27,
      "rooms_available": 27,
      "rooms_oocupied": 0
    },
    {
      "property_id": 21,
      "property_name": "My Home # 21",
      "total_floor": 3,
      "category_name": "Four Occupancy",
      "property_type_id": 1,
      "Property_Loc": "M G Road,Bangalore",
      "Property_image": "http://cdn.home-designing.com/wp-content/uploads/2022/05/home-design-Indonesia.jpg",
      "img_ct": 1,
      "video_ct": 0,
      "total_rooms": 36,
      "rooms_available": 36,
      "rooms_oocupied": 0
    },
    {
      "property_id": 6,
      "property_name": "Kalpataru Apartments",
      "total_floor": 3,
      "category_name": "Triple Occupancy",
      "property_type_id": 1,
      "Property_Loc": "M G Road,Bangalore",
      "Property_image": "http://cdn.home-designing.com/wp-content/uploads/2014/07/three-bedroom-floor-plans.jpeg",
      "img_ct": 2,
      "video_ct": 0,
      "total_rooms": 18,
      "rooms_available": 18,
      "rooms_oocupied": 0
    },
    {
      "property_id": 4,
      "property_name": "Ranka View Apartment",
      "total_floor": 3,
      "category_name": "Double Occupancy",
      "property_type_id": 1,
      "Property_Loc": "M G Road,Bangalore",
      "Property_image": "http://cdn.home-designing.com/wp-content/uploads/2022/05/modern-house-with-pool.jpg",
      "img_ct": 2,
      "video_ct": 0,
      "total_rooms": 27,
      "rooms_available": 27,
      "rooms_oocupied": 0
    },
    {
      "property_id": 18,
      "property_name": "LandT Mulberry",
      "total_floor": 3,
      "category_name": "Four Occupancy",
      "property_type_id": 1,
      "Property_Loc": "M G Road,Bangalore",
      "Property_image": "http://cdn.home-designing.com/wp-content/uploads/2022/05/Brazilian-summer-house.jpg",
      "img_ct": 2,
      "video_ct": 0,
      "total_rooms": 36,
      "rooms_available": 36,
      "rooms_oocupied": 0
    },
    {
      "property_id": 25,
      "property_name": "My Home # 25",
      "total_floor": 3,
      "category_name": "Single Occupancy",
      "property_type_id": 1,
      "Property_Loc": "M G Road,Bangalore",
      "Property_image": "http://cdn.home-designing.com/wp-content/uploads/2014/07/three-bedroom-floor-plans.jpeg",
      "img_ct": 1,
      "video_ct": 0,
      "total_rooms": 9,
      "rooms_available": 9,
      "rooms_oocupied": 0
    },
    {
      "property_id": 11,
      "property_name": "New Property # 11",
      "total_floor": 3,
      "category_name": "Double Occupancy",
      "property_type_id": 1,
      "Property_Loc": "M G Road,Bangalore",
      "Property_image": "http://cdn.home-designing.com/wp-content/uploads/2022/05/Brazilian-summer-house.jpg",
      "img_ct": 1,
      "video_ct": 0,
      "total_rooms": 27,
      "rooms_available": 27,
      "rooms_oocupied": 0
    },
    {
      "property_id": 17,
      "property_name": "New Property # 17",
      "total_floor": 3,
      "category_name": "Triple Occupancy",
      "property_type_id": 1,
      "Property_Loc": "M G Road,Bangalore",
      "Property_image": "http://cdn.home-designing.com/wp-content/uploads/2014/07/three-bedroom-floor-plans.jpeg",
      "img_ct": 1,
      "video_ct": 0,
      "total_rooms": 18,
      "rooms_available": 18,
      "rooms_oocupied": 0
    },
    {
      "property_id": 25,
      "property_name": "My Home # 25",
      "total_floor": 3,
      "category_name": "Single Occupancy",
      "property_type_id": 1,
      "Property_Loc": "M G Road,Bangalore",
      "Property_image": "http://cdn.home-designing.com/wp-content/uploads/2014/07/three-bedroom-floor-plans.jpeg",
      "img_ct": 1,
      "video_ct": 0,
      "total_rooms": 9,
      "rooms_available": 9,
      "rooms_oocupied": 0
    },
    {
      "property_id": 22,
      "property_name": "My Home # 22",
      "total_floor": 3,
      "category_name": "Four Occupancy",
      "property_type_id": 1,
      "Property_Loc": "M G Road,Bangalore",
      "Property_image": "http://cdn.home-designing.com/wp-content/uploads/2022/05/modern-house-with-pool.jpg",
      "img_ct": 1,
      "video_ct": 0,
      "total_rooms": 36,
      "rooms_available": 36,
      "rooms_oocupied": 0
    },
    {
      "property_id": 6,
      "property_name": "Kalpataru Apartments",
      "total_floor": 3,
      "category_name": "Single Occupancy",
      "property_type_id": 1,
      "Property_Loc": "M G Road,Bangalore",
      "Property_image": "http://cdn.home-designing.com/wp-content/uploads/2014/07/three-bedroom-floor-plans.jpeg",
      "img_ct": 2,
      "video_ct": 0,
      "total_rooms": 9,
      "rooms_available": 9,
      "rooms_oocupied": 0
    },
    {
      "property_id": 10,
      "property_name": "suriyas avenue",
      "total_floor": 3,
      "category_name": "Double Occupancy",
      "property_type_id": 1,
      "Property_Loc": "M G Road,Bangalore",
      "Property_image": "http://cdn.home-designing.com/wp-content/uploads/2016/01/inspiring-bedroom-accent-wall.jpg",
      "img_ct": 1,
      "video_ct": 0,
      "total_rooms": 27,
      "rooms_available": 27,
      "rooms_oocupied": 0
    },
    {
      "property_id": 23,
      "property_name": "New Property # 23",
      "total_floor": 3,
      "category_name": "Triple Occupancy",
      "property_type_id": 1,
      "Property_Loc": "M G Road,Bangalore",
      "Property_image": "http://cdn.home-designing.com/wp-content/uploads/2022/05/terazzo-pillar.jpg",
      "img_ct": 1,
      "video_ct": 0,
      "total_rooms": 18,
      "rooms_available": 18,
      "rooms_oocupied": 0
    },
    {
      "property_id": 7,
      "property_name": "New Property # 7",
      "total_floor": 3,
      "category_name": "Double Occupancy",
      "property_type_id": 1,
      "Property_Loc": "M G Road,Bangalore",
      "Property_image": "http://cdn.home-designing.com/wp-content/uploads/2022/05/terazzo-pillar.jpg",
      "img_ct": 1,
      "video_ct": 0,
      "total_rooms": 27,
      "rooms_available": 27,
      "rooms_oocupied": 0
    },
    {
      "property_id": 13,
      "property_name": "New Property # 13",
      "total_floor": 3,
      "category_name": "Double Occupancy",
      "property_type_id": 1,
      "Property_Loc": "M G Road,Bangalore",
      "Property_image": "http://cdn.home-designing.com/wp-content/uploads/2022/05/home-design-Indonesia.jpg",
      "img_ct": 1,
      "video_ct": 0,
      "total_rooms": 27,
      "rooms_available": 27,
      "rooms_oocupied": 0
    },
    {
      "property_id": 25,
      "property_name": "My Home # 25",
      "total_floor": 3,
      "category_name": "Triple Occupancy",
      "property_type_id": 1,
      "Property_Loc": "M G Road,Bangalore",
      "Property_image": "http://cdn.home-designing.com/wp-content/uploads/2014/07/three-bedroom-floor-plans.jpeg",
      "img_ct": 1,
      "video_ct": 0,
      "total_rooms": 18,
      "rooms_available": 18,
      "rooms_oocupied": 0
    },
    {
      "property_id": 9,
      "property_name": "New Property # 9",
      "total_floor": 3,
      "category_name": "Single Occupancy",
      "property_type_id": 1,
      "Property_Loc": "M G Road,Bangalore",
      "Property_image": "http://cdn.home-designing.com/wp-content/uploads/2014/07/three-bedroom-floor-plans.jpeg",
      "img_ct": 1,
      "video_ct": 0,
      "total_rooms": 9,
      "rooms_available": 9,
      "rooms_oocupied": 0
    },
    {
      "property_id": 12,
      "property_name": "New Property # 12",
      "total_floor": 3,
      "category_name": "Double Occupancy",
      "property_type_id": 1,
      "Property_Loc": "M G Road,Bangalore",
      "Property_image": "http://cdn.home-designing.com/wp-content/uploads/2022/05/green-living-room.jpg",
      "img_ct": 1,
      "video_ct": 0,
      "total_rooms": 27,
      "rooms_available": 27,
      "rooms_oocupied": 0
    },
    {
      "property_id": 8,
      "property_name": "My Home # 8",
      "total_floor": 3,
      "category_name": "Triple Occupancy",
      "property_type_id": 1,
      "Property_Loc": "M G Road,Bangalore",
      "Property_image": "https://img.staticmb.com/mbimages/project/Photo_h310_w462/2021/04/26/Project-Photo-3-Sai-Florence-Chennai-5257515_600_800_310_462.jpg",
      "img_ct": 1,
      "video_ct": 0,
      "total_rooms": 18,
      "rooms_available": 18,
      "rooms_oocupied": 0
    },
    {
      "property_id": 12,
      "property_name": "New Property # 12",
      "total_floor": 3,
      "category_name": "Double Occupancy",
      "property_type_id": 1,
      "Property_Loc": "M G Road,Bangalore",
      "Property_image": "http://cdn.home-designing.com/wp-content/uploads/2022/05/green-living-room.jpg",
      "img_ct": 1,
      "video_ct": 0,
      "total_rooms": 27,
      "rooms_available": 27,
      "rooms_oocupied": 0
    },
    {
      "property_id": 22,
      "property_name": "My Home # 22",
      "total_floor": 3,
      "category_name": "Single Occupancy",
      "property_type_id": 1,
      "Property_Loc": "M G Road,Bangalore",
      "Property_image": "http://cdn.home-designing.com/wp-content/uploads/2022/05/modern-house-with-pool.jpg",
      "img_ct": 1,
      "video_ct": 0,
      "total_rooms": 9,
      "rooms_available": 9,
      "rooms_oocupied": 0
    },
    {
      "property_id": 21,
      "property_name": "My Home # 21",
      "total_floor": 3,
      "category_name": "Single Occupancy",
      "property_type_id": 1,
      "Property_Loc": "M G Road,Bangalore",
      "Property_image": "http://cdn.home-designing.com/wp-content/uploads/2022/05/home-design-Indonesia.jpg",
      "img_ct": 1,
      "video_ct": 0,
      "total_rooms": 9,
      "rooms_available": 9,
      "rooms_oocupied": 0
    },
    {
      "property_id": 12,
      "property_name": "New Property # 12",
      "total_floor": 3,
      "category_name": "Single Occupancy",
      "property_type_id": 1,
      "Property_Loc": "M G Road,Bangalore",
      "Property_image": "http://cdn.home-designing.com/wp-content/uploads/2022/05/green-living-room.jpg",
      "img_ct": 1,
      "video_ct": 0,
      "total_rooms": 9,
      "rooms_available": 9,
      "rooms_oocupied": 0
    },
    {
      "property_id": 4,
      "property_name": "Ranka View Apartment",
      "total_floor": 3,
      "category_name": "Double Occupancy",
      "property_type_id": 1,
      "Property_Loc": "M G Road,Bangalore",
      "Property_image": "http://cdn.home-designing.com/wp-content/uploads/2022/05/modern-house-with-pool.jpg",
      "img_ct": 2,
      "video_ct": 0,
      "total_rooms": 27,
      "rooms_available": 27,
      "rooms_oocupied": 0
    },
    {
      "property_id": 9,
      "property_name": "New Property # 9",
      "total_floor": 3,
      "category_name": "Four Occupancy",
      "property_type_id": 1,
      "Property_Loc": "M G Road,Bangalore",
      "Property_image": "http://cdn.home-designing.com/wp-content/uploads/2014/07/three-bedroom-floor-plans.jpeg",
      "img_ct": 1,
      "video_ct": 0,
      "total_rooms": 36,
      "rooms_available": 36,
      "rooms_oocupied": 0
    },
    {
      "property_id": 12,
      "property_name": "New Property # 12",
      "total_floor": 3,
      "category_name": "Four Occupancy",
      "property_type_id": 1,
      "Property_Loc": "M G Road,Bangalore",
      "Property_image": "http://cdn.home-designing.com/wp-content/uploads/2022/05/green-living-room.jpg",
      "img_ct": 1,
      "video_ct": 0,
      "total_rooms": 36,
      "rooms_available": 36,
      "rooms_oocupied": 0
    },
    {
      "property_id": 18,
      "property_name": "LandT Mulberry",
      "total_floor": 3,
      "category_name": "Single Occupancy",
      "property_type_id": 1,
      "Property_Loc": "M G Road,Bangalore",
      "Property_image": "http://cdn.home-designing.com/wp-content/uploads/2022/05/Brazilian-summer-house.jpg",
      "img_ct": 2,
      "video_ct": 0,
      "total_rooms": 9,
      "rooms_available": 9,
      "rooms_oocupied": 0
    },
    {
      "property_id": 25,
      "property_name": "My Home # 25",
      "total_floor": 3,
      "category_name": "Four Occupancy",
      "property_type_id": 1,
      "Property_Loc": "M G Road,Bangalore",
      "Property_image": "http://cdn.home-designing.com/wp-content/uploads/2014/07/three-bedroom-floor-plans.jpeg",
      "img_ct": 1,
      "video_ct": 0,
      "total_rooms": 36,
      "rooms_available": 36,
      "rooms_oocupied": 0
    },
    {
      "property_id": 20,
      "property_name": "New Property # 20",
      "total_floor": 3,
      "category_name": "Double Occupancy",
      "property_type_id": 1,
      "Property_Loc": "M G Road,Bangalore",
      "Property_image": "http://cdn.home-designing.com/wp-content/uploads/2022/05/green-living-room.jpg",
      "img_ct": 1,
      "video_ct": 0,
      "total_rooms": 27,
      "rooms_available": 27,
      "rooms_oocupied": 0
    },
    {
      "property_id": 6,
      "property_name": "Kalpataru Apartments",
      "total_floor": 3,
      "category_name": "Four Occupancy",
      "property_type_id": 1,
      "Property_Loc": "M G Road,Bangalore",
      "Property_image": "http://cdn.home-designing.com/wp-content/uploads/2014/07/three-bedroom-floor-plans.jpeg",
      "img_ct": 2,
      "video_ct": 0,
      "total_rooms": 36,
      "rooms_available": 36,
      "rooms_oocupied": 0
    },
    {
      "property_id": 3,
      "property_name": "suriyas avenue",
      "total_floor": 3,
      "category_name": "Triple Occupancy",
      "property_type_id": 1,
      "Property_Loc": "M G Road,Bangalore",
      "Property_image": "http://cdn.home-designing.com/wp-content/uploads/2022/05/home-design-Indonesia.jpg",
      "img_ct": 2,
      "video_ct": 0,
      "total_rooms": 18,
      "rooms_available": 18,
      "rooms_oocupied": 0
    },
    {
      "property_id": 9,
      "property_name": "New Property # 9",
      "total_floor": 3,
      "category_name": "Double Occupancy",
      "property_type_id": 1,
      "Property_Loc": "M G Road,Bangalore",
      "Property_image": "http://cdn.home-designing.com/wp-content/uploads/2014/07/three-bedroom-floor-plans.jpeg",
      "img_ct": 1,
      "video_ct": 0,
      "total_rooms": 27,
      "rooms_available": 27,
      "rooms_oocupied": 0
    },
    {
      "property_id": 24,
      "property_name": "My Property # 24",
      "total_floor": 3,
      "category_name": "Single Occupancy",
      "property_type_id": 1,
      "Property_Loc": "M G Road,Bangalore",
      "Property_image": "https://img.staticmb.com/mbimages/project/Photo_h310_w462/2021/04/26/Project-Photo-3-Sai-Florence-Chennai-5257515_600_800_310_462.jpg",
      "img_ct": 1,
      "video_ct": 0,
      "total_rooms": 9,
      "rooms_available": 9,
      "rooms_oocupied": 0
    },
    {
      "property_id": 10,
      "property_name": "suriyas avenue",
      "total_floor": 3,
      "category_name": "Four Occupancy",
      "property_type_id": 1,
      "Property_Loc": "M G Road,Bangalore",
      "Property_image": "http://cdn.home-designing.com/wp-content/uploads/2016/01/inspiring-bedroom-accent-wall.jpg",
      "img_ct": 1,
      "video_ct": 0,
      "total_rooms": 36,
      "rooms_available": 36,
      "rooms_oocupied": 0
    },
    {
      "property_id": 7,
      "property_name": "New Property # 7",
      "total_floor": 3,
      "category_name": "Single Occupancy",
      "property_type_id": 1,
      "Property_Loc": "M G Road,Bangalore",
      "Property_image": "http://cdn.home-designing.com/wp-content/uploads/2022/05/terazzo-pillar.jpg",
      "img_ct": 1,
      "video_ct": 0,
      "total_rooms": 9,
      "rooms_available": 9,
      "rooms_oocupied": 0
    },
    {
      "property_id": 19,
      "property_name": "My Property # 19",
      "total_floor": 3,
      "category_name": "Single Occupancy",
      "property_type_id": 1,
      "Property_Loc": "M G Road,Bangalore",
      "Property_image": "http://cdn.home-designing.com/wp-content/uploads/2022/05/Brazilian-summer-house.jpg",
      "img_ct": 1,
      "video_ct": 0,
      "total_rooms": 9,
      "rooms_available": 9,
      "rooms_oocupied": 0
    },
    {
      "property_id": 3,
      "property_name": "suriyas avenue",
      "total_floor": 3,
      "category_name": "Four Occupancy",
      "property_type_id": 1,
      "Property_Loc": "M G Road,Bangalore",
      "Property_image": "http://cdn.home-designing.com/wp-content/uploads/2022/05/home-design-Indonesia.jpg",
      "img_ct": 2,
      "video_ct": 0,
      "total_rooms": 36,
      "rooms_available": 36,
      "rooms_oocupied": 0
    },
    {
      "property_id": 5,
      "property_name": "My Property # 5",
      "total_floor": 3,
      "category_name": "Double Occupancy",
      "property_type_id": 1,
      "Property_Loc": "M G Road,Bangalore",
      "Property_image": "http://cdn.home-designing.com/wp-content/uploads/2022/05/home-design-Indonesia.jpg",
      "img_ct": 1,
      "video_ct": 0,
      "total_rooms": 27,
      "rooms_available": 27,
      "rooms_oocupied": 0
    },
    {
      "property_id": 18,
      "property_name": "LandT Mulberry",
      "total_floor": 3,
      "category_name": "Single Occupancy",
      "property_type_id": 1,
      "Property_Loc": "M G Road,Bangalore",
      "Property_image": "http://cdn.home-designing.com/wp-content/uploads/2022/05/Brazilian-summer-house.jpg",
      "img_ct": 2,
      "video_ct": 0,
      "total_rooms": 9,
      "rooms_available": 9,
      "rooms_oocupied": 0
    },
    {
      "property_id": 22,
      "property_name": "My Home # 22",
      "total_floor": 3,
      "category_name": "Double Occupancy",
      "property_type_id": 1,
      "Property_Loc": "M G Road,Bangalore",
      "Property_image": "http://cdn.home-designing.com/wp-content/uploads/2022/05/modern-house-with-pool.jpg",
      "img_ct": 1,
      "video_ct": 0,
      "total_rooms": 27,
      "rooms_available": 27,
      "rooms_oocupied": 0
    },
    {
      "property_id": 24,
      "property_name": "My Property # 24",
      "total_floor": 3,
      "category_name": "Double Occupancy",
      "property_type_id": 1,
      "Property_Loc": "M G Road,Bangalore",
      "Property_image": "https://img.staticmb.com/mbimages/project/Photo_h310_w462/2021/04/26/Project-Photo-3-Sai-Florence-Chennai-5257515_600_800_310_462.jpg",
      "img_ct": 1,
      "video_ct": 0,
      "total_rooms": 27,
      "rooms_available": 27,
      "rooms_oocupied": 0
    },
    {
      "property_id": 3,
      "property_name": "suriyas avenue",
      "total_floor": 3,
      "category_name": "Double Occupancy",
      "property_type_id": 1,
      "Property_Loc": "M G Road,Bangalore",
      "Property_image": "http://cdn.home-designing.com/wp-content/uploads/2022/05/home-design-Indonesia.jpg",
      "img_ct": 2,
      "video_ct": 0,
      "total_rooms": 27,
      "rooms_available": 27,
      "rooms_oocupied": 0
    },
    {
      "property_id": 14,
      "property_name": "Nest Homes",
      "total_floor": 3,
      "category_name": "Single Occupancy",
      "property_type_id": 1,
      "Property_Loc": "M G Road,Bangalore",
      "Property_image": "http://cdn.home-designing.com/wp-content/uploads/2022/05/green-living-room.jpg",
      "img_ct": 2,
      "video_ct": 0,
      "total_rooms": 9,
      "rooms_available": 9,
      "rooms_oocupied": 0
    },
    {
      "property_id": 14,
      "property_name": "Nest Homes",
      "total_floor": 3,
      "category_name": "Triple Occupancy",
      "property_type_id": 1,
      "Property_Loc": "M G Road,Bangalore",
      "Property_image": "http://cdn.home-designing.com/wp-content/uploads/2022/05/green-living-room.jpg",
      "img_ct": 2,
      "video_ct": 0,
      "total_rooms": 18,
      "rooms_available": 18,
      "rooms_oocupied": 0
    },
    {
      "property_id": 13,
      "property_name": "New Property # 13",
      "total_floor": 3,
      "category_name": "Single Occupancy",
      "property_type_id": 1,
      "Property_Loc": "M G Road,Bangalore",
      "Property_image": "http://cdn.home-designing.com/wp-content/uploads/2022/05/home-design-Indonesia.jpg",
      "img_ct": 1,
      "video_ct": 0,
      "total_rooms": 9,
      "rooms_available": 9,
      "rooms_oocupied": 0
    },
    {
      "property_id": 2,
      "property_name": "Eden Garden",
      "total_floor": 3,
      "category_name": "Triple Occupancy",
      "property_type_id": 1,
      "Property_Loc": "M G Road,Bangalore",
      "Property_image": "http://cdn.home-designing.com/wp-content/uploads/2022/05/terazzo-pillar.jpg",
      "img_ct": 2,
      "video_ct": 0,
      "total_rooms": 18,
      "rooms_available": 18,
      "rooms_oocupied": 0
    },
    {
      "property_id": 19,
      "property_name": "My Property # 19",
      "total_floor": 3,
      "category_name": "Four Occupancy",
      "property_type_id": 1,
      "Property_Loc": "M G Road,Bangalore",
      "Property_image": "http://cdn.home-designing.com/wp-content/uploads/2022/05/Brazilian-summer-house.jpg",
      "img_ct": 1,
      "video_ct": 0,
      "total_rooms": 36,
      "rooms_available": 36,
      "rooms_oocupied": 0
    },
    {
      "property_id": 19,
      "property_name": "My Property # 19",
      "total_floor": 3,
      "category_name": "Triple Occupancy",
      "property_type_id": 1,
      "Property_Loc": "M G Road,Bangalore",
      "Property_image": "http://cdn.home-designing.com/wp-content/uploads/2022/05/Brazilian-summer-house.jpg",
      "img_ct": 1,
      "video_ct": 0,
      "total_rooms": 18,
      "rooms_available": 18,
      "rooms_oocupied": 0
    },
    {
      "property_id": 20,
      "property_name": "New Property # 20",
      "total_floor": 3,
      "category_name": "Single Occupancy",
      "property_type_id": 1,
      "Property_Loc": "M G Road,Bangalore",
      "Property_image": "http://cdn.home-designing.com/wp-content/uploads/2022/05/green-living-room.jpg",
      "img_ct": 1,
      "video_ct": 0,
      "total_rooms": 9,
      "rooms_available": 9,
      "rooms_oocupied": 0
    },
    {
      "property_id": 1,
      "property_name": "Yolo Test",
      "total_floor": 3,
      "category_name": "Triple Occupancy",
      "property_type_id": 1,
      "Property_Loc": "M G Road,Bangalore",
      "Property_image": "http://cdn.home-designing.com/wp-content/uploads/2014/07/three-bedroom-floor-plans.jpeg",
      "img_ct": 1,
      "video_ct": 0,
      "total_rooms": 18,
      "rooms_available": 18,
      "rooms_oocupied": 0
    },
    {
      "property_id": 4,
      "property_name": "Ranka View Apartment",
      "total_floor": 3,
      "category_name": "Triple Occupancy",
      "property_type_id": 1,
      "Property_Loc": "M G Road,Bangalore",
      "Property_image": "http://cdn.home-designing.com/wp-content/uploads/2022/05/modern-house-with-pool.jpg",
      "img_ct": 2,
      "video_ct": 0,
      "total_rooms": 18,
      "rooms_available": 18,
      "rooms_oocupied": 0
    },
    {
      "property_id": 11,
      "property_name": "New Property # 11",
      "total_floor": 3,
      "category_name": "Triple Occupancy",
      "property_type_id": 1,
      "Property_Loc": "M G Road,Bangalore",
      "Property_image": "http://cdn.home-designing.com/wp-content/uploads/2022/05/Brazilian-summer-house.jpg",
      "img_ct": 1,
      "video_ct": 0,
      "total_rooms": 18,
      "rooms_available": 18,
      "rooms_oocupied": 0
    },
    {
      "property_id": 8,
      "property_name": "My Home # 8",
      "total_floor": 3,
      "category_name": "Double Occupancy",
      "property_type_id": 1,
      "Property_Loc": "M G Road,Bangalore",
      "Property_image": "https://img.staticmb.com/mbimages/project/Photo_h310_w462/2021/04/26/Project-Photo-3-Sai-Florence-Chennai-5257515_600_800_310_462.jpg",
      "img_ct": 1,
      "video_ct": 0,
      "total_rooms": 27,
      "rooms_available": 27,
      "rooms_oocupied": 0
    },
    {
      "property_id": 5,
      "property_name": "My Property # 5",
      "total_floor": 3,
      "category_name": "Double Occupancy",
      "property_type_id": 1,
      "Property_Loc": "M G Road,Bangalore",
      "Property_image": "http://cdn.home-designing.com/wp-content/uploads/2022/05/home-design-Indonesia.jpg",
      "img_ct": 1,
      "video_ct": 0,
      "total_rooms": 27,
      "rooms_available": 27,
      "rooms_oocupied": 0
    },
    {
      "property_id": 25,
      "property_name": "My Home # 25",
      "total_floor": 3,
      "category_name": "Double Occupancy",
      "property_type_id": 1,
      "Property_Loc": "M G Road,Bangalore",
      "Property_image": "http://cdn.home-designing.com/wp-content/uploads/2014/07/three-bedroom-floor-plans.jpeg",
      "img_ct": 1,
      "video_ct": 0,
      "total_rooms": 27,
      "rooms_available": 27,
      "rooms_oocupied": 0
    },
    {
      "property_id": 8,
      "property_name": "My Home # 8",
      "total_floor": 3,
      "category_name": "Single Occupancy",
      "property_type_id": 1,
      "Property_Loc": "M G Road,Bangalore",
      "Property_image": "https://img.staticmb.com/mbimages/project/Photo_h310_w462/2021/04/26/Project-Photo-3-Sai-Florence-Chennai-5257515_600_800_310_462.jpg",
      "img_ct": 1,
      "video_ct": 0,
      "total_rooms": 9,
      "rooms_available": 9,
      "rooms_oocupied": 0
    },
    {
      "property_id": 6,
      "property_name": "Kalpataru Apartments",
      "total_floor": 3,
      "category_name": "Double Occupancy",
      "property_type_id": 1,
      "Property_Loc": "M G Road,Bangalore",
      "Property_image": "http://cdn.home-designing.com/wp-content/uploads/2014/07/three-bedroom-floor-plans.jpeg",
      "img_ct": 2,
      "video_ct": 0,
      "total_rooms": 27,
      "rooms_available": 27,
      "rooms_oocupied": 0
    },
    {
      "property_id": 1,
      "property_name": "Yolo Test",
      "total_floor": 3,
      "category_name": "Double Occupancy",
      "property_type_id": 1,
      "Property_Loc": "M G Road,Bangalore",
      "Property_image": "http://cdn.home-designing.com/wp-content/uploads/2014/07/three-bedroom-floor-plans.jpeg",
      "img_ct": 1,
      "video_ct": 0,
      "total_rooms": 27,
      "rooms_available": 27,
      "rooms_oocupied": 0
    },
    {
      "property_id": 21,
      "property_name": "My Home # 21",
      "total_floor": 3,
      "category_name": "Triple Occupancy",
      "property_type_id": 1,
      "Property_Loc": "M G Road,Bangalore",
      "Property_image": "http://cdn.home-designing.com/wp-content/uploads/2022/05/home-design-Indonesia.jpg",
      "img_ct": 1,
      "video_ct": 0,
      "total_rooms": 18,
      "rooms_available": 18,
      "rooms_oocupied": 0
    },
    {
      "property_id": 17,
      "property_name": "New Property # 17",
      "total_floor": 3,
      "category_name": "Double Occupancy",
      "property_type_id": 1,
      "Property_Loc": "M G Road,Bangalore",
      "Property_image": "http://cdn.home-designing.com/wp-content/uploads/2014/07/three-bedroom-floor-plans.jpeg",
      "img_ct": 1,
      "video_ct": 0,
      "total_rooms": 27,
      "rooms_available": 27,
      "rooms_oocupied": 0
    },
    {
      "property_id": 1,
      "property_name": "Yolo Test",
      "total_floor": 3,
      "category_name": "Single Occupancy",
      "property_type_id": 1,
      "Property_Loc": "M G Road,Bangalore",
      "Property_image": "http://cdn.home-designing.com/wp-content/uploads/2014/07/three-bedroom-floor-plans.jpeg",
      "img_ct": 1,
      "video_ct": 0,
      "total_rooms": 9,
      "rooms_available": 8,
      "rooms_oocupied": 1
    },
    {
      "property_id": 16,
      "property_name": "My Property # 16",
      "total_floor": 3,
      "category_name": "Single Occupancy",
      "property_type_id": 1,
      "Property_Loc": "M G Road,Bangalore",
      "Property_image": "https://img.staticmb.com/mbimages/project/Photo_h310_w462/2021/04/26/Project-Photo-3-Sai-Florence-Chennai-5257515_600_800_310_462.jpg",
      "img_ct": 1,
      "video_ct": 0,
      "total_rooms": 9,
      "rooms_available": 9,
      "rooms_oocupied": 0
    },
    {
      "property_id": 15,
      "property_name": "My Property # 15",
      "total_floor": 3,
      "category_name": "Single Occupancy",
      "property_type_id": 1,
      "Property_Loc": "M G Road,Bangalore",
      "Property_image": "http://cdn.home-designing.com/wp-content/uploads/2022/05/terazzo-pillar.jpg",
      "img_ct": 1,
      "video_ct": 0,
      "total_rooms": 9,
      "rooms_available": 9,
      "rooms_oocupied": 0
    },
    {
      "property_id": 5,
      "property_name": "My Property # 5",
      "total_floor": 3,
      "category_name": "Four Occupancy",
      "property_type_id": 1,
      "Property_Loc": "M G Road,Bangalore",
      "Property_image": "http://cdn.home-designing.com/wp-content/uploads/2022/05/home-design-Indonesia.jpg",
      "img_ct": 1,
      "video_ct": 0,
      "total_rooms": 36,
      "rooms_available": 36,
      "rooms_oocupied": 0
    },
    {
      "property_id": 10,
      "property_name": "suriyas avenue",
      "total_floor": 3,
      "category_name": "Single Occupancy",
      "property_type_id": 1,
      "Property_Loc": "M G Road,Bangalore",
      "Property_image": "http://cdn.home-designing.com/wp-content/uploads/2016/01/inspiring-bedroom-accent-wall.jpg",
      "img_ct": 1,
      "video_ct": 0,
      "total_rooms": 9,
      "rooms_available": 9,
      "rooms_oocupied": 0
    },
    {
      "property_id": 11,
      "property_name": "New Property # 11",
      "total_floor": 3,
      "category_name": "Four Occupancy",
      "property_type_id": 1,
      "Property_Loc": "M G Road,Bangalore",
      "Property_image": "http://cdn.home-designing.com/wp-content/uploads/2022/05/Brazilian-summer-house.jpg",
      "img_ct": 1,
      "video_ct": 0,
      "total_rooms": 36,
      "rooms_available": 36,
      "rooms_oocupied": 0
    },
    {
      "property_id": 23,
      "property_name": "New Property # 23",
      "total_floor": 3,
      "category_name": "Single Occupancy",
      "property_type_id": 1,
      "Property_Loc": "M G Road,Bangalore",
      "Property_image": "http://cdn.home-designing.com/wp-content/uploads/2022/05/terazzo-pillar.jpg",
      "img_ct": 1,
      "video_ct": 0,
      "total_rooms": 9,
      "rooms_available": 9,
      "rooms_oocupied": 0
    },
    {
      "property_id": 11,
      "property_name": "New Property # 11",
      "total_floor": 3,
      "category_name": "Double Occupancy",
      "property_type_id": 1,
      "Property_Loc": "M G Road,Bangalore",
      "Property_image": "http://cdn.home-designing.com/wp-content/uploads/2022/05/Brazilian-summer-house.jpg",
      "img_ct": 1,
      "video_ct": 0,
      "total_rooms": 27,
      "rooms_available": 27,
      "rooms_oocupied": 0
    },
    {
      "property_id": 9,
      "property_name": "New Property # 9",
      "total_floor": 3,
      "category_name": "Single Occupancy",
      "property_type_id": 1,
      "Property_Loc": "M G Road,Bangalore",
      "Property_image": "http://cdn.home-designing.com/wp-content/uploads/2014/07/three-bedroom-floor-plans.jpeg",
      "img_ct": 1,
      "video_ct": 0,
      "total_rooms": 9,
      "rooms_available": 9,
      "rooms_oocupied": 0
    },
    {
      "property_id": 1,
      "property_name": "Yolo Test",
      "total_floor": 3,
      "category_name": "Single Occupancy",
      "property_type_id": 1,
      "Property_Loc": "M G Road,Bangalore",
      "Property_image": "http://cdn.home-designing.com/wp-content/uploads/2014/07/three-bedroom-floor-plans.jpeg",
      "img_ct": 1,
      "video_ct": 0,
      "total_rooms": 9,
      "rooms_available": 8,
      "rooms_oocupied": 1
    },
    {
      "property_id": 2,
      "property_name": "Eden Garden",
      "total_floor": 3,
      "category_name": "Single Occupancy",
      "property_type_id": 1,
      "Property_Loc": "M G Road,Bangalore",
      "Property_image": "http://cdn.home-designing.com/wp-content/uploads/2022/05/terazzo-pillar.jpg",
      "img_ct": 2,
      "video_ct": 0,
      "total_rooms": 9,
      "rooms_available": 9,
      "rooms_oocupied": 0
    },
    {
      "property_id": 23,
      "property_name": "New Property # 23",
      "total_floor": 3,
      "category_name": "Four Occupancy",
      "property_type_id": 1,
      "Property_Loc": "M G Road,Bangalore",
      "Property_image": "http://cdn.home-designing.com/wp-content/uploads/2022/05/terazzo-pillar.jpg",
      "img_ct": 1,
      "video_ct": 0,
      "total_rooms": 36,
      "rooms_available": 36,
      "rooms_oocupied": 0
    },
    {
      "property_id": 3,
      "property_name": "suriyas avenue",
      "total_floor": 3,
      "category_name": "Single Occupancy",
      "property_type_id": 1,
      "Property_Loc": "M G Road,Bangalore",
      "Property_image": "http://cdn.home-designing.com/wp-content/uploads/2022/05/home-design-Indonesia.jpg",
      "img_ct": 2,
      "video_ct": 0,
      "total_rooms": 9,
      "rooms_available": 9,
      "rooms_oocupied": 0
    },
    {
      "property_id": 5,
      "property_name": "My Property # 5",
      "total_floor": 3,
      "category_name": "Triple Occupancy",
      "property_type_id": 1,
      "Property_Loc": "M G Road,Bangalore",
      "Property_image": "http://cdn.home-designing.com/wp-content/uploads/2022/05/home-design-Indonesia.jpg",
      "img_ct": 1,
      "video_ct": 0,
      "total_rooms": 18,
      "rooms_available": 18,
      "rooms_oocupied": 0
    },
    {
      "property_id": 14,
      "property_name": "Nest Homes",
      "total_floor": 3,
      "category_name": "Double Occupancy",
      "property_type_id": 1,
      "Property_Loc": "M G Road,Bangalore",
      "Property_image": "http://cdn.home-designing.com/wp-content/uploads/2022/05/green-living-room.jpg",
      "img_ct": 2,
      "video_ct": 0,
      "total_rooms": 27,
      "rooms_available": 27,
      "rooms_oocupied": 0
    },
    {
      "property_id": 18,
      "property_name": "LandT Mulberry",
      "total_floor": 3,
      "category_name": "Double Occupancy",
      "property_type_id": 1,
      "Property_Loc": "M G Road,Bangalore",
      "Property_image": "http://cdn.home-designing.com/wp-content/uploads/2022/05/Brazilian-summer-house.jpg",
      "img_ct": 2,
      "video_ct": 0,
      "total_rooms": 27,
      "rooms_available": 27,
      "rooms_oocupied": 0
    },
    {
      "property_id": 1,
      "property_name": "Yolo Test",
      "total_floor": 3,
      "category_name": "Single Occupancy",
      "property_type_id": 1,
      "Property_Loc": "M G Road,Bangalore",
      "Property_image": "http://cdn.home-designing.com/wp-content/uploads/2014/07/three-bedroom-floor-plans.jpeg",
      "img_ct": 1,
      "video_ct": 0,
      "total_rooms": 9,
      "rooms_available": 8,
      "rooms_oocupied": 1
    },
    {
      "property_id": 13,
      "property_name": "New Property # 13",
      "total_floor": 3,
      "category_name": "Four Occupancy",
      "property_type_id": 1,
      "Property_Loc": "M G Road,Bangalore",
      "Property_image": "http://cdn.home-designing.com/wp-content/uploads/2022/05/home-design-Indonesia.jpg",
      "img_ct": 1,
      "video_ct": 0,
      "total_rooms": 36,
      "rooms_available": 36,
      "rooms_oocupied": 0
    },
    {
      "property_id": 13,
      "property_name": "New Property # 13",
      "total_floor": 3,
      "category_name": "Single Occupancy",
      "property_type_id": 1,
      "Property_Loc": "M G Road,Bangalore",
      "Property_image": "http://cdn.home-designing.com/wp-content/uploads/2022/05/home-design-Indonesia.jpg",
      "img_ct": 1,
      "video_ct": 0,
      "total_rooms": 9,
      "rooms_available": 9,
      "rooms_oocupied": 0
    },
    {
      "property_id": 17,
      "property_name": "New Property # 17",
      "total_floor": 3,
      "category_name": "Four Occupancy",
      "property_type_id": 1,
      "Property_Loc": "M G Road,Bangalore",
      "Property_image": "http://cdn.home-designing.com/wp-content/uploads/2014/07/three-bedroom-floor-plans.jpeg",
      "img_ct": 1,
      "video_ct": 0,
      "total_rooms": 36,
      "rooms_available": 36,
      "rooms_oocupied": 0
    },
    {
      "property_id": 24,
      "property_name": "My Property # 24",
      "total_floor": 3,
      "category_name": "Triple Occupancy",
      "property_type_id": 1,
      "Property_Loc": "M G Road,Bangalore",
      "Property_image": "https://img.staticmb.com/mbimages/project/Photo_h310_w462/2021/04/26/Project-Photo-3-Sai-Florence-Chennai-5257515_600_800_310_462.jpg",
      "img_ct": 1,
      "video_ct": 0,
      "total_rooms": 18,
      "rooms_available": 18,
      "rooms_oocupied": 0
    },
    {
      "property_id": 4,
      "property_name": "Ranka View Apartment",
      "total_floor": 3,
      "category_name": "Single Occupancy",
      "property_type_id": 1,
      "Property_Loc": "M G Road,Bangalore",
      "Property_image": "http://cdn.home-designing.com/wp-content/uploads/2022/05/modern-house-with-pool.jpg",
      "img_ct": 2,
      "video_ct": 0,
      "total_rooms": 9,
      "rooms_available": 9,
      "rooms_oocupied": 0
    },
    {
      "property_id": 19,
      "property_name": "My Property # 19",
      "total_floor": 3,
      "category_name": "Single Occupancy",
      "property_type_id": 1,
      "Property_Loc": "M G Road,Bangalore",
      "Property_image": "http://cdn.home-designing.com/wp-content/uploads/2022/05/Brazilian-summer-house.jpg",
      "img_ct": 1,
      "video_ct": 0,
      "total_rooms": 9,
      "rooms_available": 9,
      "rooms_oocupied": 0
    },
    {
      "property_id": 12,
      "property_name": "New Property # 12",
      "total_floor": 3,
      "category_name": "Single Occupancy",
      "property_type_id": 1,
      "Property_Loc": "M G Road,Bangalore",
      "Property_image": "http://cdn.home-designing.com/wp-content/uploads/2022/05/green-living-room.jpg",
      "img_ct": 1,
      "video_ct": 0,
      "total_rooms": 9,
      "rooms_available": 9,
      "rooms_oocupied": 0
    },
    {
      "property_id": 15,
      "property_name": "My Property # 15",
      "total_floor": 3,
      "category_name": "Four Occupancy",
      "property_type_id": 1,
      "Property_Loc": "M G Road,Bangalore",
      "Property_image": "http://cdn.home-designing.com/wp-content/uploads/2022/05/terazzo-pillar.jpg",
      "img_ct": 1,
      "video_ct": 0,
      "total_rooms": 36,
      "rooms_available": 36,
      "rooms_oocupied": 0
    },
    {
      "property_id": 5,
      "property_name": "My Property # 5",
      "total_floor": 3,
      "category_name": "Single Occupancy",
      "property_type_id": 1,
      "Property_Loc": "M G Road,Bangalore",
      "Property_image": "http://cdn.home-designing.com/wp-content/uploads/2022/05/home-design-Indonesia.jpg",
      "img_ct": 1,
      "video_ct": 0,
      "total_rooms": 9,
      "rooms_available": 9,
      "rooms_oocupied": 0
    },
    {
      "property_id": 2,
      "property_name": "Eden Garden",
      "total_floor": 3,
      "category_name": "Double Occupancy",
      "property_type_id": 1,
      "Property_Loc": "M G Road,Bangalore",
      "Property_image": "http://cdn.home-designing.com/wp-content/uploads/2022/05/terazzo-pillar.jpg",
      "img_ct": 2,
      "video_ct": 0,
      "total_rooms": 27,
      "rooms_available": 27,
      "rooms_oocupied": 0
    },
    {
      "property_id": 1,
      "property_name": "Yolo Test",
      "total_floor": 3,
      "category_name": "Four Occupancy",
      "property_type_id": 1,
      "Property_Loc": "M G Road,Bangalore",
      "Property_image": "http://cdn.home-designing.com/wp-content/uploads/2014/07/three-bedroom-floor-plans.jpeg",
      "img_ct": 1,
      "video_ct": 0,
      "total_rooms": 36,
      "rooms_available": 36,
      "rooms_oocupied": 0
    },
    {
      "property_id": 2,
      "property_name": "Eden Garden",
      "total_floor": 3,
      "category_name": "Double Occupancy",
      "property_type_id": 1,
      "Property_Loc": "M G Road,Bangalore",
      "Property_image": "http://cdn.home-designing.com/wp-content/uploads/2022/05/terazzo-pillar.jpg",
      "img_ct": 2,
      "video_ct": 0,
      "total_rooms": 27,
      "rooms_available": 27,
      "rooms_oocupied": 0
    },
    {
      "property_id": 11,
      "property_name": "New Property # 11",
      "total_floor": 3,
      "category_name": "Single Occupancy",
      "property_type_id": 1,
      "Property_Loc": "M G Road,Bangalore",
      "Property_image": "http://cdn.home-designing.com/wp-content/uploads/2022/05/Brazilian-summer-house.jpg",
      "img_ct": 1,
      "video_ct": 0,
      "total_rooms": 9,
      "rooms_available": 9,
      "rooms_oocupied": 0
    },
    {
      "property_id": 6,
      "property_name": "Kalpataru Apartments",
      "total_floor": 3,
      "category_name": "Double Occupancy",
      "property_type_id": 1,
      "Property_Loc": "M G Road,Bangalore",
      "Property_image": "http://cdn.home-designing.com/wp-content/uploads/2014/07/three-bedroom-floor-plans.jpeg",
      "img_ct": 2,
      "video_ct": 0,
      "total_rooms": 27,
      "rooms_available": 27,
      "rooms_oocupied": 0
    },
    {
      "property_id": 10,
      "property_name": "suriyas avenue",
      "total_floor": 3,
      "category_name": "Double Occupancy",
      "property_type_id": 1,
      "Property_Loc": "M G Road,Bangalore",
      "Property_image": "http://cdn.home-designing.com/wp-content/uploads/2016/01/inspiring-bedroom-accent-wall.jpg",
      "img_ct": 1,
      "video_ct": 0,
      "total_rooms": 27,
      "rooms_available": 27,
      "rooms_oocupied": 0
    },
    {
      "property_id": 16,
      "property_name": "My Property # 16",
      "total_floor": 3,
      "category_name": "Triple Occupancy",
      "property_type_id": 1,
      "Property_Loc": "M G Road,Bangalore",
      "Property_image": "https://img.staticmb.com/mbimages/project/Photo_h310_w462/2021/04/26/Project-Photo-3-Sai-Florence-Chennai-5257515_600_800_310_462.jpg",
      "img_ct": 1,
      "video_ct": 0,
      "total_rooms": 18,
      "rooms_available": 18,
      "rooms_oocupied": 0
    },
    {
      "property_id": 7,
      "property_name": "New Property # 7",
      "total_floor": 3,
      "category_name": "Four Occupancy",
      "property_type_id": 1,
      "Property_Loc": "M G Road,Bangalore",
      "Property_image": "http://cdn.home-designing.com/wp-content/uploads/2022/05/terazzo-pillar.jpg",
      "img_ct": 1,
      "video_ct": 0,
      "total_rooms": 36,
      "rooms_available": 36,
      "rooms_oocupied": 0
    },
    {
      "property_id": 2,
      "property_name": "Eden Garden",
      "total_floor": 3,
      "category_name": "Single Occupancy",
      "property_type_id": 1,
      "Property_Loc": "M G Road,Bangalore",
      "Property_image": "http://cdn.home-designing.com/wp-content/uploads/2022/05/terazzo-pillar.jpg",
      "img_ct": 2,
      "video_ct": 0,
      "total_rooms": 9,
      "rooms_available": 9,
      "rooms_oocupied": 0
    },
    {
      "property_id": 8,
      "property_name": "My Home # 8",
      "total_floor": 3,
      "category_name": "Four Occupancy",
      "property_type_id": 1,
      "Property_Loc": "M G Road,Bangalore",
      "Property_image": "https://img.staticmb.com/mbimages/project/Photo_h310_w462/2021/04/26/Project-Photo-3-Sai-Florence-Chennai-5257515_600_800_310_462.jpg",
      "img_ct": 1,
      "video_ct": 0,
      "total_rooms": 36,
      "rooms_available": 36,
      "rooms_oocupied": 0
    },
    {
      "property_id": 3,
      "property_name": "suriyas avenue",
      "total_floor": 3,
      "category_name": "Single Occupancy",
      "property_type_id": 1,
      "Property_Loc": "M G Road,Bangalore",
      "Property_image": "http://cdn.home-designing.com/wp-content/uploads/2022/05/home-design-Indonesia.jpg",
      "img_ct": 2,
      "video_ct": 0,
      "total_rooms": 9,
      "rooms_available": 9,
      "rooms_oocupied": 0
    },
    {
      "property_id": 9,
      "property_name": "New Property # 9",
      "total_floor": 3,
      "category_name": "Triple Occupancy",
      "property_type_id": 1,
      "Property_Loc": "M G Road,Bangalore",
      "Property_image": "http://cdn.home-designing.com/wp-content/uploads/2014/07/three-bedroom-floor-plans.jpeg",
      "img_ct": 1,
      "video_ct": 0,
      "total_rooms": 18,
      "rooms_available": 18,
      "rooms_oocupied": 0
    },
    {
      "property_id": 20,
      "property_name": "New Property # 20",
      "total_floor": 3,
      "category_name": "Single Occupancy",
      "property_type_id": 1,
      "Property_Loc": "M G Road,Bangalore",
      "Property_image": "http://cdn.home-designing.com/wp-content/uploads/2022/05/green-living-room.jpg",
      "img_ct": 1,
      "video_ct": 0,
      "total_rooms": 9,
      "rooms_available": 9,
      "rooms_oocupied": 0
    },
    {
      "property_id": 24,
      "property_name": "My Property # 24",
      "total_floor": 3,
      "category_name": "Four Occupancy",
      "property_type_id": 1,
      "Property_Loc": "M G Road,Bangalore",
      "Property_image": "https://img.staticmb.com/mbimages/project/Photo_h310_w462/2021/04/26/Project-Photo-3-Sai-Florence-Chennai-5257515_600_800_310_462.jpg",
      "img_ct": 1,
      "video_ct": 0,
      "total_rooms": 36,
      "rooms_available": 36,
      "rooms_oocupied": 0
    },
    {
      "property_id": 7,
      "property_name": "New Property # 7",
      "total_floor": 3,
      "category_name": "Single Occupancy",
      "property_type_id": 1,
      "Property_Loc": "M G Road,Bangalore",
      "Property_image": "http://cdn.home-designing.com/wp-content/uploads/2022/05/terazzo-pillar.jpg",
      "img_ct": 1,
      "video_ct": 0,
      "total_rooms": 9,
      "rooms_available": 9,
      "rooms_oocupied": 0
    },
    {
      "property_id": 9,
      "property_name": "New Property # 9",
      "total_floor": 3,
      "category_name": "Double Occupancy",
      "property_type_id": 1,
      "Property_Loc": "M G Road,Bangalore",
      "Property_image": "http://cdn.home-designing.com/wp-content/uploads/2014/07/three-bedroom-floor-plans.jpeg",
      "img_ct": 1,
      "video_ct": 0,
      "total_rooms": 27,
      "rooms_available": 27,
      "rooms_oocupied": 0
    },
    {
      "property_id": 8,
      "property_name": "My Home # 8",
      "total_floor": 3,
      "category_name": "Double Occupancy",
      "property_type_id": 1,
      "Property_Loc": "M G Road,Bangalore",
      "Property_image": "https://img.staticmb.com/mbimages/project/Photo_h310_w462/2021/04/26/Project-Photo-3-Sai-Florence-Chennai-5257515_600_800_310_462.jpg",
      "img_ct": 1,
      "video_ct": 0,
      "total_rooms": 27,
      "rooms_available": 27,
      "rooms_oocupied": 0
    },
    {
      "property_id": 15,
      "property_name": "My Property # 15",
      "total_floor": 3,
      "category_name": "Single Occupancy",
      "property_type_id": 1,
      "Property_Loc": "M G Road,Bangalore",
      "Property_image": "http://cdn.home-designing.com/wp-content/uploads/2022/05/terazzo-pillar.jpg",
      "img_ct": 1,
      "video_ct": 0,
      "total_rooms": 9,
      "rooms_available": 9,
      "rooms_oocupied": 0
    },
    {
      "property_id": 10,
      "property_name": "suriyas avenue",
      "total_floor": 3,
      "category_name": "Single Occupancy",
      "property_type_id": 1,
      "Property_Loc": "M G Road,Bangalore",
      "Property_image": "http://cdn.home-designing.com/wp-content/uploads/2016/01/inspiring-bedroom-accent-wall.jpg",
      "img_ct": 1,
      "video_ct": 0,
      "total_rooms": 9,
      "rooms_available": 9,
      "rooms_oocupied": 0
    },
    {
      "property_id": 7,
      "property_name": "New Property # 7",
      "total_floor": 3,
      "category_name": "Triple Occupancy",
      "property_type_id": 1,
      "Property_Loc": "M G Road,Bangalore",
      "Property_image": "http://cdn.home-designing.com/wp-content/uploads/2022/05/terazzo-pillar.jpg",
      "img_ct": 1,
      "video_ct": 0,
      "total_rooms": 18,
      "rooms_available": 18,
      "rooms_oocupied": 0
    },
    {
      "property_id": 22,
      "property_name": "My Home # 22",
      "total_floor": 3,
      "category_name": "Single Occupancy",
      "property_type_id": 1,
      "Property_Loc": "M G Road,Bangalore",
      "Property_image": "http://cdn.home-designing.com/wp-content/uploads/2022/05/modern-house-with-pool.jpg",
      "img_ct": 1,
      "video_ct": 0,
      "total_rooms": 9,
      "rooms_available": 9,
      "rooms_oocupied": 0
    },
    {
      "property_id": 23,
      "property_name": "New Property # 23",
      "total_floor": 3,
      "category_name": "Single Occupancy",
      "property_type_id": 1,
      "Property_Loc": "M G Road,Bangalore",
      "Property_image": "http://cdn.home-designing.com/wp-content/uploads/2022/05/terazzo-pillar.jpg",
      "img_ct": 1,
      "video_ct": 0,
      "total_rooms": 9,
      "rooms_available": 9,
      "rooms_oocupied": 0
    },
    {
      "property_id": 20,
      "property_name": "New Property # 20",
      "total_floor": 3,
      "category_name": "Triple Occupancy",
      "property_type_id": 1,
      "Property_Loc": "M G Road,Bangalore",
      "Property_image": "http://cdn.home-designing.com/wp-content/uploads/2022/05/green-living-room.jpg",
      "img_ct": 1,
      "video_ct": 0,
      "total_rooms": 18,
      "rooms_available": 18,
      "rooms_oocupied": 0
    },
    {
      "property_id": 4,
      "property_name": "Ranka View Apartment",
      "total_floor": 3,
      "category_name": "Single Occupancy",
      "property_type_id": 1,
      "Property_Loc": "M G Road,Bangalore",
      "Property_image": "http://cdn.home-designing.com/wp-content/uploads/2022/05/modern-house-with-pool.jpg",
      "img_ct": 2,
      "video_ct": 0,
      "total_rooms": 9,
      "rooms_available": 9,
      "rooms_oocupied": 0
    },
    {
      "property_id": 12,
      "property_name": "New Property # 12",
      "total_floor": 3,
      "category_name": "Triple Occupancy",
      "property_type_id": 1,
      "Property_Loc": "M G Road,Bangalore",
      "Property_image": "http://cdn.home-designing.com/wp-content/uploads/2022/05/green-living-room.jpg",
      "img_ct": 1,
      "video_ct": 0,
      "total_rooms": 18,
      "rooms_available": 18,
      "rooms_oocupied": 0
    },
    {
      "property_id": 16,
      "property_name": "My Property # 16",
      "total_floor": 3,
      "category_name": "Single Occupancy",
      "property_type_id": 1,
      "Property_Loc": "M G Road,Bangalore",
      "Property_image": "https://img.staticmb.com/mbimages/project/Photo_h310_w462/2021/04/26/Project-Photo-3-Sai-Florence-Chennai-5257515_600_800_310_462.jpg",
      "img_ct": 1,
      "video_ct": 0,
      "total_rooms": 9,
      "rooms_available": 9,
      "rooms_oocupied": 0
    },
    {
      "property_id": 24,
      "property_name": "My Property # 24",
      "total_floor": 3,
      "category_name": "Single Occupancy",
      "property_type_id": 1,
      "Property_Loc": "M G Road,Bangalore",
      "Property_image": "https://img.staticmb.com/mbimages/project/Photo_h310_w462/2021/04/26/Project-Photo-3-Sai-Florence-Chennai-5257515_600_800_310_462.jpg",
      "img_ct": 1,
      "video_ct": 0,
      "total_rooms": 9,
      "rooms_available": 9,
      "rooms_oocupied": 0
    },
    {
      "property_id": 6,
      "property_name": "Kalpataru Apartments",
      "total_floor": 3,
      "category_name": "Single Occupancy",
      "property_type_id": 1,
      "Property_Loc": "M G Road,Bangalore",
      "Property_image": "http://cdn.home-designing.com/wp-content/uploads/2014/07/three-bedroom-floor-plans.jpeg",
      "img_ct": 2,
      "video_ct": 0,
      "total_rooms": 9,
      "rooms_available": 9,
      "rooms_oocupied": 0
    },
    {
      "property_id": 2,
      "property_name": "Eden Garden",
      "total_floor": 3,
      "category_name": "Four Occupancy",
      "property_type_id": 1,
      "Property_Loc": "M G Road,Bangalore",
      "Property_image": "http://cdn.home-designing.com/wp-content/uploads/2022/05/terazzo-pillar.jpg",
      "img_ct": 2,
      "video_ct": 0,
      "total_rooms": 36,
      "rooms_available": 36,
      "rooms_oocupied": 0
    },
    {
      "property_id": 1,
      "property_name": "Yolo Test",
      "total_floor": 3,
      "category_name": "Double Occupancy",
      "property_type_id": 1,
      "Property_Loc": "M G Road,Bangalore",
      "Property_image": "http://cdn.home-designing.com/wp-content/uploads/2014/07/three-bedroom-floor-plans.jpeg",
      "img_ct": 1,
      "video_ct": 0,
      "total_rooms": 27,
      "rooms_available": 27,
      "rooms_oocupied": 0
    },
    {
      "property_id": 18,
      "property_name": "LandT Mulberry",
      "total_floor": 3,
      "category_name": "Triple Occupancy",
      "property_type_id": 1,
      "Property_Loc": "M G Road,Bangalore",
      "Property_image": "http://cdn.home-designing.com/wp-content/uploads/2022/05/Brazilian-summer-house.jpg",
      "img_ct": 2,
      "video_ct": 0,
      "total_rooms": 18,
      "rooms_available": 18,
      "rooms_oocupied": 0
    },
    {
      "property_id": 11,
      "property_name": "New Property # 11",
      "total_floor": 3,
      "category_name": "Single Occupancy",
      "property_type_id": 1,
      "Property_Loc": "M G Road,Bangalore",
      "Property_image": "http://cdn.home-designing.com/wp-content/uploads/2022/05/Brazilian-summer-house.jpg",
      "img_ct": 1,
      "video_ct": 0,
      "total_rooms": 9,
      "rooms_available": 9,
      "rooms_oocupied": 0
    },
    {
      "property_id": 17,
      "property_name": "New Property # 17",
      "total_floor": 3,
      "category_name": "Single Occupancy",
      "property_type_id": 1,
      "Property_Loc": "M G Road,Bangalore",
      "Property_image": "http://cdn.home-designing.com/wp-content/uploads/2014/07/three-bedroom-floor-plans.jpeg",
      "img_ct": 1,
      "video_ct": 0,
      "total_rooms": 9,
      "rooms_available": 9,
      "rooms_oocupied": 0
    }
  ]
  